datasink_api_client/__init__.py
datasink_api_client/async_client.py
datasink_api_client/client.py
datasink_api_client/models.py
cl01_ZGF0YXNpbms-1.dist-info/METADATA
cl01_ZGF0YXNpbms-1.dist-info/WHEEL
cl01_ZGF0YXNpbms-1.dist-info/top_level.txt
cl01_ZGF0YXNpbms-1.dist-info/RECORD
