Metadata-Version: 2.1
Name: cl01-ZGF0YXNpbms
Version: 1
Classifier: Programming Language :: Python :: 3
Classifier: Operating System :: OS Independent
Requires-Python: <4.0,>=3.10
Requires-Dist: requests
Requires-Dist: pydantic
Requires-Dist: httpx
